<?xml version="1.0" encoding="UTF-8" standalone="no"?>
<root>
	<transicion>
		<qi>0</qi>
		<si>a</si>
		<qj>2</qj>
		<sj>x</sj>
		<movimiento>R</movimiento>
	</transicion>
	<transicion>
		<qi>0</qi>
		<si>b</si>
		<qj>5</qj>
		<sj>x</sj>
		<movimiento>R</movimiento>
	</transicion>
	<transicion>
		<qi>0</qi>
		<si>c</si>
		<qj>7</qj>
		<sj>c</sj>
		<movimiento>R</movimiento>
	</transicion>
	<transicion>
		<qi>1</qi>
		<si>a</si>
		<qj>2</qj>
		<sj>x</sj>
		<movimiento>R</movimiento>
	</transicion>
	<transicion>
		<qi>1</qi>
		<si>b</si>
		<qj>5</qj>
		<sj>x</sj>
		<movimiento>R</movimiento>
	</transicion>
	<transicion>
		<qi>1</qi>
		<si>c</si>
		<qj>8</qj>
		<sj>c</sj>
		<movimiento>R</movimiento>
	</transicion>
	<transicion>
		<qi>2</qi>
		<si>a</si>
		<qj>2</qj>
		<sj>a</sj>
		<movimiento>R</movimiento>
	</transicion>
	<transicion>
		<qi>2</qi>
		<si>b</si>
		<qj>2</qj>
		<sj>b</sj>
		<movimiento>R</movimiento>
	</transicion>
	<transicion>
		<qi>2</qi>
		<si>c</si>
		<qj>3</qj>
		<sj>c</sj>
		<movimiento>R</movimiento>
	</transicion>
	<transicion>
		<qi>3</qi>
		<si>a</si>
		<qj>4</qj>
		<sj>y</sj>
		<movimiento>L</movimiento>
	</transicion>
	<transicion>
		<qi>3</qi>
		<si>y</si>
		<qj>3</qj>
		<sj>y</sj>
		<movimiento>R</movimiento>
	</transicion>
	<transicion>
		<qi>4</qi>
		<si>a</si>
		<qj>4</qj>
		<sj>a</sj>
		<movimiento>L</movimiento>
	</transicion>
	<transicion>
		<qi>4</qi>
		<si>b</si>
		<qj>4</qj>
		<sj>b</sj>
		<movimiento>L</movimiento>
	</transicion>
	<transicion>
		<qi>4</qi>
		<si>c</si>
		<qj>4</qj>
		<sj>c</sj>
		<movimiento>L</movimiento>
	</transicion>
	<transicion>
		<qi>4</qi>
		<si>y</si>
		<qj>4</qj>
		<sj>y</sj>
		<movimiento>L</movimiento>
	</transicion>
	<transicion>
		<qi>4</qi>
		<si>x</si>
		<qj>1</qj>
		<sj>x</sj>
		<movimiento>R</movimiento>
	</transicion>
	<transicion>
		<qi>5</qi>
		<si>a</si>
		<qj>5</qj>
		<sj>a</sj>
		<movimiento>R</movimiento>
	</transicion>
	<transicion>
		<qi>5</qi>
		<si>b</si>
		<qj>5</qj>
		<sj>b</sj>
		<movimiento>R</movimiento>
	</transicion>
	<transicion>
		<qi>5</qi>
		<si>c</si>
		<qj>6</qj>
		<sj>c</sj>
		<movimiento>R</movimiento>
	</transicion>
	<transicion>
		<qi>6</qi>
		<si>b</si>
		<qj>4</qj>
		<sj>y</sj>
		<movimiento>L</movimiento>
	</transicion>
	<transicion>
		<qi>6</qi>
		<si>y</si>
		<qj>6</qj>
		<sj>y</sj>
		<movimiento>R</movimiento>
	</transicion>
	<transicion>
		<qi>7</qi>
		<si>#</si>
		<qj>9</qj>
		<sj>#</sj>
		<movimiento>E</movimiento>
	</transicion>
	<transicion>
		<qi>8</qi>
		<si>y</si>
		<qj>8</qj>
		<sj>y</sj>
		<movimiento>R</movimiento>
	</transicion>
	<transicion>
		<qi>8</qi>
		<si>#</si>
		<qj>9</qj>
		<sj>#</sj>
		<movimiento>E</movimiento>
	</transicion>
	<transicion>
		<qi>9</qi>
	</transicion>	
</root>